regexploit/__init__.py
regexploit/found_regex.py
regexploit/hook.py
regexploit/redos.py
regexploit/ast/__init__.py
regexploit/ast/at.py
regexploit/ast/branch.py
regexploit/ast/categories.py
regexploit/ast/char.py
regexploit/ast/groupref.py
regexploit/ast/ranges.py
regexploit/ast/repeat.py
regexploit/ast/sequence.py
regexploit/ast/sre.py
regexploit/bin/__init__.py
regexploit/bin/files.py
regexploit/bin/regexploit-python-env
regexploit/bin/regexploit.py
regexploit/bin/regexploit_csharp.py
regexploit/bin/regexploit_js.py
regexploit/bin/regexploit_python_ast.py
regexploit/bin/regexploit_yaml.py
regexploit/bin/javascript/cli.js
regexploit/bin/javascript/find.js
regexploit/bin/javascript/index.js
regexploit/bin/javascript/package-lock.json
regexploit/bin/javascript/package.json
regexploit/languages/__init__.py
regexploit/languages/csharp_string_extractor.py
regexploit/languages/javascript.py
regexploit/languages/python_node_visitor.py
regexploit/output/__init__.py
regexploit/output/text.py
regexploit-1.0.0.data/scripts/regexploit-python-env
regexploit-1.0.0.dist-info/LICENSE
regexploit-1.0.0.dist-info/METADATA
regexploit-1.0.0.dist-info/WHEEL
regexploit-1.0.0.dist-info/entry_points.txt
regexploit-1.0.0.dist-info/top_level.txt
regexploit-1.0.0.dist-info/RECORD
