Metadata-Version: 2.1
Name: regexploit
Version: 1.0.0
Summary: Find regular expressions vulnerable to ReDoS
Home-page: https://github.com/doyensec/regexploit
Author: Ben Caller :: Doyensec
Author-email: REMOVETHISPREFIX.ben@doyensec.com
License: UNKNOWN
Platform: UNKNOWN
Classifier: Programming Language :: Python :: 3
Classifier: License :: OSI Approved :: Apache Software License
Classifier: Operating System :: OS Independent
Requires-Python: >=3.8
Provides-Extra: yaml
Requires-Dist: pyyaml (>=5.3.1) ; extra == 'yaml'
